LICENSE
README.md
setup.py
hrsii/__init__.py
hrsii/axioms.py
hrsii/datasets.py
hrsii/hrsii.py
hrsii/plot.py
hrsii/utils.py
hrsii.egg-info/PKG-INFO
hrsii.egg-info/SOURCES.txt
hrsii.egg-info/dependency_links.txt
hrsii.egg-info/requires.txt
hrsii.egg-info/top_level.txt
hrsii/data/S2_10m.json
hrsii/data/bands.json
hrsii/data/constants.json
hrsii/data/spectral-indices-dict.json
hrsii/data/spectral.json
tests/test_hrsii.py